dart_id/__init__.py
dart_id/align.py
dart_id/collator.py
dart_id/converter.py
dart_id/exceptions.py
dart_id/fido_cpp_interface.py
dart_id/figures.py
dart_id/helper.py
dart_id/models.py
dart_id/update.py
dart_id/version.py
dart_id/config/defaults.yaml
dart_id/config/schema.yaml
dart_id/fido/BayesianNetwork.py
dart_id/fido/BinomialHeap.py
dart_id/fido/Fido MIT license.txt
dart_id/fido/GraphUtilities.py
dart_id/fido/Utilities.py
dart_id/fido/__init__.py
dart_id/figure_gen/__init__.py
dart_id/figure_gen/exp_alignment.py
dart_id/figure_gen/newpeps.py
dart_id/figure_gen/residuals.py
dart_id/figure_resources/bootstrap.min.css
dart_id/figure_resources/bootstrap.min.js
dart_id/figure_resources/jquery-3.3.1.slim.min.js
dart_id/figure_resources/jquery.dataTables.min.css
dart_id/figure_resources/jquery.dataTables.min.js
dart_id/figure_resources/styles.css
dart_id/figure_resources/template.html
dart_id/models/fit_RT3e.stan
dart_id/models/fit_RT_linear.stan
dart_id/models/fit_RT3e/debian/fit_RT3e
dart_id/models/fit_RT3e/linux_generic/fit_RT3e
dart_id/models/fit_RT3e/mac/fit_RT3e
dart_id/models/fit_RT3e/rhel/fit_RT3e
dart_id/models/fit_RT3e/windows/fit_RT3e.exe
dart_id/models/fit_RT3e/windows/libwinpthread-1.dll
dart_id-2.0.7.dist-info/LICENSE.txt
dart_id-2.0.7.dist-info/METADATA
dart_id-2.0.7.dist-info/WHEEL
dart_id-2.0.7.dist-info/entry_points.txt
dart_id-2.0.7.dist-info/top_level.txt
dart_id-2.0.7.dist-info/RECORD
