Metadata-Version: 2.1
Name: dart-id
Version: 2.0.7
Summary: RT Alignment and Peptide ID Confidence Updating for LC-MS/MS Data
Home-page: https://github.com/SlavovLab/DART-ID
Author: Albert Chen
Author-email: chen.alb@husky.neu.edu
License: MIT
Project-URL: Documentation, https://github.com/SlavovLab/DART-ID
Project-URL: Source, https://github.com/SlavovLab/DART-ID
Project-URL: Tracker, https://github.com/SlavovLab/DART-ID/issues
Project-URL: Lab Page, https://web.northeastern.edu/slavovlab/
Keywords: bayesian retention time psm peptide spectra update
Platform: UNKNOWN
Classifier: Development Status :: 4 - Beta
Classifier: Environment :: Console
Classifier: Intended Audience :: Developers
Classifier: Intended Audience :: Science/Research
Classifier: License :: OSI Approved :: MIT License
Classifier: Programming Language :: Python :: 3 :: Only
Classifier: Programming Language :: Python :: 3.4
Classifier: Programming Language :: Python :: 3.5
Classifier: Programming Language :: Python :: 3.6
Classifier: Programming Language :: Python :: 3.7
Classifier: Topic :: Scientific/Engineering :: Bio-Informatics
Requires-Dist: pyyaml (>=3.12)
Requires-Dist: numpy (>=1.14.3)
Requires-Dist: scipy (>=1.0.0)
Requires-Dist: pandas (>=0.22.0)
Requires-Dist: matplotlib (>=2.1.2)
Requires-Dist: networkx (<2.3,>=2.1)
Requires-Dist: jsonschema (>=3.0.1)
